langcoin/__init__.py
langcoin/signals.py
langcoin-0.2.1.dist-info/METADATA
langcoin-0.2.1.dist-info/WHEEL
langcoin-0.2.1.dist-info/top_level.txt
langcoin-0.2.1.dist-info/RECORD
