Metadata-Version: 2.1
Name: langcoin
Version: 0.2.1
Summary: Automatic LCOIN trading signals in your LangChain and Web3 workflows
Home-page: UNKNOWN
License: UNKNOWN
Platform: UNKNOWN
Classifier: Development Status :: 4 - Beta
Classifier: Intended Audience :: Developers
Classifier: Programming Language :: Python :: 3
Classifier: Programming Language :: Python :: 3.8
Classifier: Programming Language :: Python :: 3.9
Classifier: Programming Language :: Python :: 3.10
Classifier: Programming Language :: Python :: 3.11
Requires-Python: >=3.8
Requires-Dist: langchain
Requires-Dist: langchain-community (>=0.0.10)
Requires-Dist: langchain-openai (>=0.0.1)
Requires-Dist: requests (>=2.28.0)
Requires-Dist: openai (>=1.0.0)
Requires-Dist: pydantic (>=2.0.0)
Requires-Dist: aiohttp (>=3.8.0)
Requires-Dist: numpy (>=1.20.0)
Requires-Dist: web3 (>=6.0.0)
